andi_datasets/__init__.py
andi_datasets/_modidx.py
andi_datasets/analysis.py
andi_datasets/datasets_challenge.py
andi_datasets/datasets_phenom.py
andi_datasets/datasets_theory.py
andi_datasets/models_phenom.py
andi_datasets/models_theory.py
andi_datasets/utils_challenge.py
andi_datasets/utils_trajectories.py
andi_datasets/utils_videos.py
andi_datasets-2.1.5.dist-info/LICENSE
andi_datasets-2.1.5.dist-info/METADATA
andi_datasets-2.1.5.dist-info/WHEEL
andi_datasets-2.1.5.dist-info/entry_points.txt
andi_datasets-2.1.5.dist-info/top_level.txt
andi_datasets-2.1.5.dist-info/RECORD
