Metadata-Version: 2.1
Name: andi-datasets
Version: 2.1.5
Summary: Generate, manage and analyze anomalous diffusion trajectories.
Home-page: https://github.com/andichallenge/andi_datasets/
Author: Gorka Munoz-Gil
Author-email: munoz.gil.gorka@gmail.com
License: Apache Software License 2.0
Keywords: anomalous diffusion
Classifier: Development Status :: 4 - Beta
Classifier: Intended Audience :: Developers
Classifier: Natural Language :: English
Classifier: Programming Language :: Python :: 3.10
Classifier: License :: OSI Approved :: Apache Software License
Requires-Python: >=3.10
License-File: LICENSE
Requires-Dist: numpy (<=1.26.4)
Requires-Dist: stochastic
Requires-Dist: tqdm
Requires-Dist: scipy
Requires-Dist: h5py
Requires-Dist: pandas
Requires-Dist: matplotlib
Requires-Dist: scikit-learn
Requires-Dist: imageio
Provides-Extra: dev
